cic_helper/Person.py
cic_helper/__init__.py
cic_helper/cli.py
cic_helper/constants.py
cic_helper/kitabu/kitabu.json
cic_helper/kitabu/kitabu.toml
cic_helper/kitabu/run.sh
cic_helper-0.2.4.dist-info/entry_points.txt
cic_helper-0.2.4.dist-info/WHEEL
cic_helper-0.2.4.dist-info/METADATA
cic_helper-0.2.4.dist-info/RECORD
