Metadata-Version: 2.1
Name: cic-helper
Version: 0.2.4
Summary: 
Author: William Luke
Author-email: williamluke4@gmail.com
Requires-Python: >=3.8,<4.0
Classifier: Programming Language :: Python :: 3
Classifier: Programming Language :: Python :: 3.10
Classifier: Programming Language :: Python :: 3.8
Classifier: Programming Language :: Python :: 3.9
Requires-Dist: chainlib-eth (>=0.1.0,<0.2.0)
Requires-Dist: click (>=8.1.2,<9.0.0)
